structas/__init__.py
structas/cli.py
structas/output.py
structas/parser.py
structas/structure.py
structas/destinations/__init__.py
structas/destinations/abstract_destination.py
structas/destinations/bigquery.py
structas/destinations/filesystem.py
structas/destinations/gcs.py
structas/k8/__init__.py
structas/k8/pod_streamer.py
structas/patterns/__init__.py
structas/patterns/grok_parser.py
structas/patterns/regex_parser.py
structas/patterns/template_parser.py
structas/utils/__init__.py
structas/utils/banner.py
structas/utils/logging.py
structas-0.1.0.dist-info/licenses/LICENSE
structas-0.1.0.dist-info/METADATA
structas-0.1.0.dist-info/WHEEL
structas-0.1.0.dist-info/entry_points.txt
structas-0.1.0.dist-info/top_level.txt
structas-0.1.0.dist-info/RECORD
