Metadata-Version: 2.4
Name: structas
Version: 0.1.0
Summary: A library for chopping logs.
Home-page: https://github.com/author/structas
Author: 
Author-email: Author <rich@gluk0.dev>
License-Expression: MIT
Project-URL: Homepage, https://github.com/gluk0/structas
Project-URL: Issues, https://github.com/gluk0/structas/issues
Classifier: Programming Language :: Python :: 3
Classifier: Programming Language :: Python :: 3.8
Classifier: Programming Language :: Python :: 3.9
Classifier: Programming Language :: Python :: 3.10
Classifier: Programming Language :: Python :: 3.11
Classifier: Operating System :: OS Independent
Requires-Python: >=3.8
License-File: LICENSE
Requires-Dist: click>=8.1.8
Requires-Dist: kubernetes>=32.0.1
Requires-Dist: pyaml>=25.1.0
Requires-Dist: pytest>=8.3.5
Requires-Dist: regex>=2024.11.6
Requires-Dist: twine>=6.1.0
Requires-Dist: typing-extensions>=4.0.0
Provides-Extra: dev
Requires-Dist: ruff>=0.1.5; extra == "dev"
Requires-Dist: pre-commit>=3.5.0; extra == "dev"
Requires-Dist: pytest>=7.4.3; extra == "dev"
Requires-Dist: pytest-cov>=4.1.0; extra == "dev"
Dynamic: home-page
Dynamic: license-file
Dynamic: requires-python
